{
    "backend": "flask",
    "db_name": "",
    "db_pass": "",
    "db_type": "sqlite",
    "db_user": "",
    "dbms": "1",
    "description": "generated product",
    "design": "datta-able",
    "docker": "1",
    "frontend": "",
    "github_repo": "https://github.com/appseed-projects/7d723744-3a32-4e45-a40a-f51518ca4b70",
    "heroku": "0",
    "pattern": "mvc",
    "pro": "0",
    "task_id": "7d723744-3a32-4e45-a40a-f51518ca4b70",
    "task_info": "Upload Sources [0%] - 138 files",
    "task_result": "SUCCESS",
    "task_state": "RUNNING",
    "task_ts_end": "2022-05-09-08-12-11",
    "task_ts_start": "2022-05-09-08-12-09"
}